AnimalProfile/File.py
AnimalProfile/Profile.py
AnimalProfile/Root.py
AnimalProfile/__init__.py
AnimalProfile/session/__init__.py
AnimalProfile/session/batchAnimals.py
AnimalProfile/session/singleAnimal.py
AnimalProfile-0.1.dist-info/LICENSE
AnimalProfile-0.1.dist-info/METADATA
AnimalProfile-0.1.dist-info/WHEEL
AnimalProfile-0.1.dist-info/top_level.txt
AnimalProfile-0.1.dist-info/RECORD
