Metadata-Version: 2.1
Name: AnimalProfile
Version: 0.1
Summary: A package for tagging animal experiments
Home-page: https://github.com/atmostafa/AnimalProfile
Author: Mostafa
Author-email: EmailAtMostafa@gmail.com
License: UNKNOWN
Download-URL: https://github.com/AtMostafa/AnimalProfile/archive/0.1.tar.gz
Platform: UNKNOWN
Classifier: Programming Language :: Python :: 3
Classifier: License :: OSI Approved :: MIT License
Classifier: Operating System :: OS Independent
Requires-Python: >=3.6
Requires-Dist: pandas
